<sequential display_name="Lab: Broadcast, Animations, and Music">
  <vertical url_name="overview-broadcast-animations-music"/>
  <vertical url_name="broadcast-animations-music_13"/>
  <vertical url_name="broadcast-animations-music_14"/>
  <vertical url_name="broadcast-animations-music_15"/>
  <vertical url_name="broadcast-animations-music_16"/>
  <vertical url_name="broadcast-animations-music_18"/>
  <vertical url_name="broadcast-animations-music_19"/>
  <vertical url_name="broadcast-animations-music_20"/>
  <vertical url_name="broadcast-animations-music_22"/>
  <vertical url_name="broadcast-animations-music_24"/>
  <vertical url_name="broadcast-animations-music_25"/>
  <vertical url_name="broadcast-animations-music_26"/>
  <vertical url_name="broadcast-animations-music_28"/>
</sequential>